code_EDA_files/part1/design.sv
`timescale 1ns / 1ns 
  
  module LEDcoder( char, LED);
    input wire[3:0] char;
    output reg [7:0] LED;
    
    //translates binary value in char to value for LED in HEX
    always @ (char)
      begin
 
        case(char) 
          4'b0000 : LED[7:0] <= 8'b00000011 ; 
          4'b0001 : LED[7:0] <= 8'b10011111 ; 
          4'b0010 : LED[7:0] <= 8'b00100101 ; 
          4'b0011 : LED[7:0] <= 8'b00001101 ; 
          4'b0100 : LED[7:0] <= 8'b10011001 ; 
          4'b0101 : LED[7:0] <= 8'b01001001 ; 
          4'b0110 : LED[7:0] <= 8'b01000001 ; 
          4'b0111 : LED[7:0] <= 8'b00011111 ; 
          4'b1000 : LED[7:0] <= 8'b00000001 ; 
          4'b1001 : LED[7:0] <= 8'b00001001 ; 
          4'b1010 : LED[7:0] <= 8'b11111101 ; 
          4'b1011 : LED[7:0] <= 8'b01110001 ; 
          4'b1100 : LED[7:0] <= 8'b11111111 ; 
        
        endcase 
    	      
	      
      end
      
  endmodule


module anodoi(clk,HEX3,HEX2,HEX1,HEX0,AN3,AN2,AN1,AN0,myHex);
  input wire clk;
  input wire [7:0] HEX3,HEX2,HEX1,HEX0;
  
  output reg [7:0] myHex;
  output reg AN3,AN2,AN1,AN0;
  
  integer cycles;
  
  //inmplement of fsm
  reg [2:0] current_state, next_state;
  parameter w_closed=3'b100,
  			w_openAN3=3'b011,
  			w_openAN2=3'b010, 
  			w_openAN1=3'b001,
  			w_openAN0=3'b000;
  

    initial
    begin
      AN0=1;
      AN1=1;
      AN2=1;
      AN3=1;
      myHex=0;
      cycles=15;
      current_state=w_closed;
      next_state=w_closed;
    end
  
  
  always @(posedge clk)
    begin
      current_state=next_state;
      
      
       if (cycles==15)
        begin
          cycles=0;
        end
      else
        cycles=cycles+1;
      
      //operation for anodes
       case (cycles)
            4'h2: AN3=0;
            4'h3: AN3=1;
            4'h6: AN2=0;
            4'h7: AN2=1;
            4'hA: AN1=0;
            4'hB: AN1=1;
            4'hE: AN0=0;
            4'hF: AN0=1;

            4'h0:myHex=HEX3;
            4'h4:myHex=HEX2;
            4'h8:myHex=HEX1;
            4'hC:myHex=HEX0;


          endcase

    end
  
  //operation for fsm
  always @(AN3,AN2,AN1,AN0)
    begin
      if (AN3==0)
        next_state=w_openAN3;
      else if (AN2==0)
        next_state=w_openAN2;
      else if (AN1==0)
        next_state=w_openAN1;
      else if (AN0==0)
        next_state=w_openAN0;
      else
        next_state=w_closed;
      
    end
 
endmodule

code_EDA_files/part1/testbench.sv
`timescale 1ns / 1ns 

module sys ;

  reg clk;
  integer cycles;
  integer theChar;
  
  wire AN3;
  wire AN2;
  wire AN1;
  wire AN0;
 
  
  reg [3:0] myChar0;
  reg [3:0] myChar1;
  reg [3:0] myChar2;
  reg [3:0] myChar3;
  
  wire [7:0] HEX0 ; 
  wire [7:0] HEX1 ; 
  wire [7:0] HEX2 ; 
  wire [7:0] HEX3 ; 
  
  wire [7:0] myHex;  
   
  //explicit port mapping
  LEDcoder disp0(myChar0, HEX0);
  LEDcoder disp1(myChar1, HEX1);
  LEDcoder disp2(myChar2, HEX2);
  LEDcoder disp3(myChar3, HEX3);
  anodoi Uo(clk,HEX3,HEX2,HEX1,HEX0,AN3,AN2,AN1,AN0,myHex);
  
  initial
    begin
      theChar=0;
      
      //number -194
      myChar3=4'b1010;
      myChar2=4'b0001;
      myChar1=4'b1001;
      myChar0=4'b0100;
      
    end
  
  
  //code for clock implementation
   initial begin
    forever begin
      clk<=1;
      #10
      clk<=0;
      #10
      clk <=1;
    end
  end
  
  //run time for our simulation
  initial begin
    #1280 $finish;
  end
  
  initial
        begin
         $dumpfile("dump.vcd"); $dumpvars;
        end
  
  initial
    begin
      cycles=15;
    end
  
  //code for data change
  always @(posedge clk)
    begin
      if (cycles==15)
        cycles=0;
      else
        cycles=cycles+1;
      
      if (cycles==15)
        begin
           theChar=theChar+1;
          
          case(theChar)
            4'h1:	//number __10
              begin
                myChar3=4'b1100;
      			myChar2=4'b1100;
      			myChar1=4'b0001;
      			myChar0=4'b0000;
              end
             4'h2:	//number _-32
              begin
                myChar3=4'b1100;
      			myChar2=4'b1010;
      			myChar1=4'b0011;
      			myChar0=4'b0010;
              end
             4'h3:	//number FFFF
              begin
                myChar3=4'b1011;
      			myChar2=4'b1011;
      			myChar1=4'b1011;
      			myChar0=4'b1011;
              end
          endcase
        end
    end
  
endmodule

code_EDA_files/part1/dump.vcd
$date
	Mon Jan 30 15:57:02 2023
$end
$version
	Icarus Verilog
$end
$timescale
	1ns
$end
$scope module sys $end
$var wire 1 ! AN0 $end
$var wire 1 " AN1 $end
$var wire 1 # AN2 $end
$var wire 1 $ AN3 $end
$var wire 8 % HEX0 [7:0] $end
$var wire 8 & HEX1 [7:0] $end
$var wire 8 ' HEX2 [7:0] $end
$var wire 8 ( HEX3 [7:0] $end
$var wire 8 ) myHex [7:0] $end
$var reg 1 * clk $end
$var integer 32 + cycles [31:0] $end
$var reg 4 , myChar0 [3:0] $end
$var reg 4 - myChar1 [3:0] $end
$var reg 4 . myChar2 [3:0] $end
$var reg 4 / myChar3 [3:0] $end
$var integer 32 0 theChar [31:0] $end
$scope module disp0 $end
$var wire 4 1 char [3:0] $end
$var reg 8 2 LED [7:0] $end
$upscope $end
$scope module disp1 $end
$var wire 4 3 char [3:0] $end
$var reg 8 4 LED [7:0] $end
$upscope $end
$scope module disp2 $end
$var wire 4 5 char [3:0] $end
$var reg 8 6 LED [7:0] $end
$upscope $end
$scope module disp3 $end
$var wire 4 7 char [3:0] $end
$var reg 8 8 LED [7:0] $end
$upscope $end
$scope module Uo $end
$var wire 8 9 HEX0 [7:0] $end
$var wire 8 : HEX1 [7:0] $end
$var wire 8 ; HEX2 [7:0] $end
$var wire 8 < HEX3 [7:0] $end
$var wire 1 = clk $end
$var reg 1 > AN0 $end
$var reg 1 ? AN1 $end
$var reg 1 @ AN2 $end
$var reg 1 A AN3 $end
$var reg 3 B current_state [2:0] $end
$var integer 32 C cycles [31:0] $end
$var reg 8 D myHex [7:0] $end
$var reg 3 E next_state [2:0] $end
$upscope $end
$upscope $end
$enddefinitions $end
#0
$dumpvars
b100 E
b11111101 D
b0 C
b100 B
1A
1@
1?
1>
1=
b11111101 <
b10011111 ;
b1001 :
b10011001 9
b11111101 8
b1010 7
b10011111 6
b1 5
b1001 4
b1001 3
b10011001 2
b100 1
b0 0
b1010 /
b1 .
b1001 -
b100 ,
b0 +
1*
b11111101 )
b11111101 (
b10011111 '
b1001 &
b10011001 %
1$
1#
1"
1!
$end
#10
0*
0=
#20
b1 +
b1 C
1*
1=
#30
0*
0=
#40
b11 E
0A
0$
b10 C
b10 +
1*
1=
#50
0*
0=
#60
b100 E
b11 +
1A
1$
b11 C
b11 B
1*
1=
#70
0*
0=
#80
b10011111 D
b10011111 )
b100 C
b100 B
b100 +
1*
1=
#90
0*
0=
#100
b101 +
b101 C
1*
1=
#110
0*
0=
#120
b10 E
0@
0#
b110 C
b110 +
1*
1=
#130
0*
0=
#140
b100 E
b111 +
1@
1#
b111 C
b10 B
1*
1=
#150
0*
0=
#160
b1001 D
b1001 )
b1000 C
b100 B
b1000 +
1*
1=
#170
0*
0=
#180
b1001 +
b1001 C
1*
1=
#190
0*
0=
#200
b1 E
0?
0"
b1010 C
b1010 +
1*
1=
#210
0*
0=
#220
b100 E
b1011 +
1?
1"
b1011 C
b1 B
1*
1=
#230
0*
0=
#240
b10011001 D
b10011001 )
b1100 C
b100 B
b1100 +
1*
1=
#250
0*
0=
#260
b1101 +
b1101 C
1*
1=
#270
0*
0=
#280
b0 E
0>
0!
b1110 C
b1110 +
1*
1=
#290
0*
0=
#300
b11 2
b11 %
b11 9
b10011111 4
b10011111 &
b10011111 :
b11111111 6
b11111111 '
b11111111 ;
b11111111 8
b11111111 (
b11111111 <
b100 E
b0 ,
b0 1
b1 -
b1 3
b1100 .
b1100 5
b1100 /
b1100 7
b1 0
b1111 +
1>
1!
b1111 C
b0 B
1*
1=
#310
0*
0=
#320
b11111111 D
b11111111 )
b0 C
b100 B
b0 +
1*
1=
#330
0*
0=
#340
b1 +
b1 C
1*
1=
#350
0*
0=
#360
b11 E
0A
0$
b10 C
b10 +
1*
1=
#370
0*
0=
#380
b100 E
b11 +
1A
1$
b11 C
b11 B
1*
1=
#390
0*
0=
#400
b100 C
b100 B
b100 +
1*
1=
#410
0*
0=
#420
b101 +
b101 C
1*
1=
#430
0*
0=
#440
b10 E
0@
0#
b110 C
b110 +
1*
1=
#450
0*
0=
#460
b100 E
b111 +
1@
1#
b111 C
b10 B
1*
1=
#470
0*
0=
#480
b10011111 D
b10011111 )
b1000 C
b100 B
b1000 +
1*
1=
#490
0*
0=
#500
b1001 +
b1001 C
1*
1=
#510
0*
0=
#520
b1 E
0?
0"
b1010 C
b1010 +
1*
1=
#530
0*
0=
#540
b100 E
b1011 +
1?
1"
b1011 C
b1 B
1*
1=
#550
0*
0=
#560
b11 D
b11 )
b1100 C
b100 B
b1100 +
1*
1=
#570
0*
0=
#580
b1101 +
b1101 C
1*
1=
#590
0*
0=
#600
b0 E
0>
0!
b1110 C
b1110 +
1*
1=
#610
0*
0=
#620
b100101 2
b100101 %
b100101 9
b1101 4
b1101 &
b1101 :
b11111101 6
b11111101 '
b11111101 ;
b100 E
b10 ,
b10 1
b11 -
b11 3
b1010 .
b1010 5
b10 0
b1111 +
1>
1!
b1111 C
b0 B
1*
1=
#630
0*
0=
#640
b11111111 D
b11111111 )
b0 C
b100 B
b0 +
1*
1=
#650
0*
0=
#660
b1 +
b1 C
1*
1=
#670
0*
0=
#680
b11 E
0A
0$
b10 C
b10 +
1*
1=
#690
0*
0=
#700
b100 E
b11 +
1A
1$
b11 C
b11 B
1*
1=
#710
0*
0=
#720
b11111101 D
b11111101 )
b100 C
b100 B
b100 +
1*
1=
#730
0*
0=
#740
b101 +
b101 C
1*
1=
#750
0*
0=
#760
b10 E
0@
0#
b110 C
b110 +
1*
1=
#770
0*
0=
#780
b100 E
b111 +
1@
1#
b111 C
b10 B
1*
1=
#790
0*
0=
#800
b1101 D
b1101 )
b1000 C
b100 B
b1000 +
1*
1=
#810
0*
0=
#820
b1001 +
b1001 C
1*
1=
#830
0*
0=
#840
b1 E
0?
0"
b1010 C
b1010 +
1*
1=
#850
0*
0=
#860
b100 E
b1011 +
1?
1"
b1011 C
b1 B
1*
1=
#870
0*
0=
#880
b100101 D
b100101 )
b1100 C
b100 B
b1100 +
1*
1=
#890
0*
0=
#900
b1101 +
b1101 C
1*
1=
#910
0*
0=
#920
b0 E
0>
0!
b1110 C
b1110 +
1*
1=
#930
0*
0=
#940
b1110001 2
b1110001 %
b1110001 9
b1110001 4
b1110001 &
b1110001 :
b1110001 6
b1110001 '
b1110001 ;
b1110001 8
b1110001 (
b1110001 <
b100 E
b1011 ,
b1011 1
b1011 -
b1011 3
b1011 .
b1011 5
b1011 /
b1011 7
b11 0
b1111 +
1>
1!
b1111 C
b0 B
1*
1=
#950
0*
0=
#960
b1110001 D
b1110001 )
b0 C
b100 B
b0 +
1*
1=
#970
0*
0=
#980
b1 +
b1 C
1*
1=
#990
0*
0=
#1000
b11 E
0A
0$
b10 C
b10 +
1*
1=
#1010
0*
0=
#1020
b100 E
b11 +
1A
1$
b11 C
b11 B
1*
1=
#1030
0*
0=
#1040
b100 C
b100 B
b100 +
1*
1=
#1050
0*
0=
#1060
b101 +
b101 C
1*
1=
#1070
0*
0=
#1080
b10 E
0@
0#
b110 C
b110 +
1*
1=
#1090
0*
0=
#1100
b100 E
b111 +
1@
1#
b111 C
b10 B
1*
1=
#1110
0*
0=
#1120
b1000 C
b100 B
b1000 +
1*
1=
#1130
0*
0=
#1140
b1001 +
b1001 C
1*
1=
#1150
0*
0=
#1160
b1 E
0?
0"
b1010 C
b1010 +
1*
1=
#1170
0*
0=
#1180
b100 E
b1011 +
1?
1"
b1011 C
b1 B
1*
1=
#1190
0*
0=
#1200
b1100 C
b100 B
b1100 +
1*
1=
#1210
0*
0=
#1220
b1101 +
b1101 C
1*
1=
#1230
0*
0=
#1240
b0 E
0>
0!
b1110 C
b1110 +
1*
1=
#1250
0*
0=
#1260
b100 E
b100 0
b1111 +
1>
1!
b1111 C
b0 B
1*
1=
#1270
0*
0=
#1280
b0 C
b100 B
b0 +
1*
1=
