code_EDA_files/part2/design.sv
`timescale 1ns/1ns

//IMPLEMANTION OF BAUD CONTROLLER
module baud_controller(reset, clk, baud_select, sample_ENABLE);
  input wire clk,reset;
  input wire [2:0] baud_select;
  output reg sample_ENABLE;
  
  reg [2:0] baudRate;
  reg [15:0] divisor;
  reg [15:0] baudCounter;
  
  
  initial
    begin
          baudCounter<=0;
          sample_ENABLE<=0;
    end
  
  //finds in clock cycles for our selection
  always @(baud_select)
  begin
    case(baud_select)
      3'b000: divisor=16'd10417;
      3'b001: divisor=16'd2604;
      3'b010: divisor=16'd651;
      3'b011: divisor=16'd326;
      3'b100: divisor=16'd163;
      3'b101: divisor=16'd81;
      3'b110: divisor=16'd54;
      3'b111: divisor=16'd27;
    endcase
  end
  
  //implementation of the sample clock
  always @(posedge clk)
    begin
      if(reset)
        begin
          baudCounter<=0;
          sample_ENABLE<=0;
        end
      else
        begin
          baudCounter<=baudCounter+1;
          if(baudCounter==(divisor-1))
            begin
              sample_ENABLE<=~sample_ENABLE;
              baudCounter<=0;
             
            end     
        end
    end
endmodule


//------------------------------------------------------------


//IMPLEMENTATION OF TRANSIMITTER
module uart_transimitter(reset,clk,Tx_Data,baud_select,Tx_WR,Tx_EN,TxD,Tx_BUSY);
  input wire reset;
  input wire clk;
  input wire [7:0] Tx_Data;
  input wire [2:0] baud_select;
  input wire Tx_WR;
  input wire Tx_EN;
  output reg TxD;
  output reg Tx_BUSY;
  
  wire Tx_sample_ENABLE;
  
  reg [3:0] tx_counter;
  reg parity_bit;

  //fsm
  reg current_state, next_state ; 
  parameter tx_on = 1'b1 ,
  			 tx_off = 1'b0 ; 
  
  			 
  //creating clock for the tx
  baud_controller baud_controller_tx_instance(reset,clk,baud_select,Tx_sample_ENABLE);
  

  initial 
    begin
     Tx_BUSY<=0;
     tx_counter<=0;
     TxD<=1;
     current_state <= tx_off ; 
     next_state <= tx_off ; 
     parity_bit<=0; 
      
      
    end 
  
  //when there are new data availiable
  always @(posedge Tx_WR) 
    begin 
      Tx_BUSY<=0;
      tx_counter<=0;
      TxD<=1;
      current_state <= tx_off ; 
      next_state <= tx_off ; 
      parity_bit<=0; 
    end 
  
  
  always @(posedge Tx_sample_ENABLE)
    begin
      if(reset)
        begin
          Tx_BUSY<=0;
          tx_counter<=0;
          TxD<=1;
          current_state <= tx_off ; 
          next_state <= tx_off ; 
          parity_bit<=0;
          
          
        end
      else
        begin
          current_state <= next_state ; 
          if(Tx_EN )
            begin
              //data transmit
             
                  Tx_BUSY<=1;
                  
                  if(tx_counter==0)
                    TxD<=1'b0; //start bit
                  else if (tx_counter==10)
                   	TxD<=1'b1; //stop bit
                  else if (tx_counter==9)
                    TxD<=parity_bit;
                  else 
                    begin
                      TxD<=Tx_Data[tx_counter-1];
                      
                      //calculates parity
                      if(Tx_Data[tx_counter-1])
                         if(parity_bit)
                            parity_bit<=0;
                        else
                          parity_bit<=1;                    
                    end
                                    
                   tx_counter<= tx_counter+1;
              
              //when transmit ends
                  if(tx_counter==11)
                    begin
                      	Tx_BUSY<=0;
                      	TxD<=1;

                      
                    end
                  
                end          

                      
        end     
    end
  
  //fsm state accordingly Tx_EN signal
  always @(Tx_EN) 
    begin 
      if( Tx_EN == 1) 
        next_state <= tx_on ; 
      else 
        next_state <= tx_off; 
    end 

endmodule
//------------------------------------------------------------

//IMPLEMENTATION OF RECEIVER
module uart_receiver (reset,clk,Rx_DATA,baud_select,Rx_EN,RxD,Rx_FERROR,Rx_PERROR,Rx_VALID);
  input wire  reset,clk;
  input wire [2:0] baud_select;
  input wire Rx_EN;
  input wire RxD;
  
  output reg [7:0] Rx_DATA;
  output reg Rx_FERROR;
  output reg Rx_PERROR; 
  output reg Rx_VALID;
  
  wire Rx_sample_ENABLE;
  
  reg [3:0] Rx_counter;
  reg Rx_parity_bit;
  reg Tx_parity_bit;
  reg state;
  reg [7:0] Rx_POS_DATA;


  
  integer i;
  
  //FSM
  reg current_state, next_state ; 
  parameter rx_on = 1'b1 ,
  			 rx_off = 1'b0 ; 
  
  //clock for the Rx
  baud_controller baud_controller_rx_instance(reset,clk,baud_select,Rx_sample_ENABLE);
  
  initial 
    begin
      
       Rx_counter<=0;
       Rx_FERROR<=0;
       Rx_PERROR<=0; 
       Rx_VALID<=0;
       state<=0;
       Rx_DATA <= 0 ; 
      current_state <= rx_off ; 
      next_state <= rx_off ; 
      Tx_parity_bit<= 0 ;
       Rx_parity_bit <= 0 ; 
    end 
  
 
  
  //checking for correct clocks between Tx and Rx
  always  @(negedge RxD)
    begin
      if (Rx_sample_ENABLE==0)
        Rx_FERROR=1;
        
    end
  
  //initiation of the signals for start of receiving
  always @(posedge Rx_EN) 
    begin 
        Rx_counter<=0;
        state<=0;
        Rx_FERROR<=0;
        Rx_PERROR<=0;
      	Rx_VALID <= 0; 
        Tx_parity_bit<= 0 ;
        Rx_parity_bit <= 0 ; 
      
    end 
  
  
  //half period after of transmiting 
  always @(negedge Rx_sample_ENABLE)
  begin
      if(reset)
        begin
          Rx_counter<=0;
          Rx_FERROR<=0;
          Rx_PERROR<=0; 
          Rx_VALID<=0;
          state<=0;
          Rx_DATA <= 0 ;
          current_state <= rx_off ; 
     	  next_state <= rx_off ; 
          Tx_parity_bit<= 0 ;
          Rx_parity_bit <= 0 ; 
          
          

        end
    //Data Receiving 
      else
        begin
          current_state <= next_state ; 
          if(Rx_EN)
           begin
            if(!RxD && !state)
              begin
                state<=1;
                Rx_counter<=Rx_counter+1;
                Rx_VALID<=0;
                Rx_parity_bit<=0;
              end
            else if (state)
              begin
                if (Rx_counter<9)
                  begin
                    Rx_POS_DATA[Rx_counter-1]<=RxD;
                    Rx_counter<=Rx_counter+1;
                    
                    //calculate parity bit
                    if(RxD)
                          if(Rx_parity_bit)
                            Rx_parity_bit<=0;
                        else
                          Rx_parity_bit<=1;
                  end
                else if (Rx_counter==9)
                  begin
                    Tx_parity_bit =RxD;
                    //Tx_parity_bit =0;
                    Rx_counter<=Rx_counter+1;
                      
                    //checking for correct parity
                    if (Rx_parity_bit!=Tx_parity_bit)
                      Rx_PERROR<=1;

                  end
                else if (Rx_counter==10)
                  begin

                    
                    //checking if the receiving is valid
                    if(!Rx_PERROR && !Rx_FERROR)
                      begin
                        Rx_VALID<=1;
                        Rx_DATA<=Rx_POS_DATA;
                      end



                  end



                  






              end	//state




          end //enable
    	end //else of reset
        
      
    end	//always block
  
  
  //fsm state accordingly Rx_EN signal
  always @(Rx_EN) 
    begin 
      if( Rx_EN == 1) 
        next_state <= rx_on ; 
      else 
        next_state <= rx_off; 
    end 


endmodule

code_EDA_files/part2/testbench.sv
`timescale 1ns/1ns

module HW2;

  reg clk;
  reg [2:0] baud_select;
  reg [2:0] wrong_baud_select;
  reg reset;
  reg [7:0] Tx_Data;
  reg Tx_WR;
  reg Tx_EN;
  reg Rx_EN;
  reg [15:0] dataToSend;

  wire TxD;
  wire Tx_BUSY;
  
  wire [7:0] Rx_DATA;
  wire Rx_FERROR;
  wire Rx_PERROR; 
  wire Rx_VALID;
  
  integer data_counter ; 
  
  
  wire sample_ENABLE;
  
  initial
    begin
      dataToSend=16'b1010100010001000;
      baud_select=3'b111;
      wrong_baud_select=3'b100;
      Tx_WR=1;
      Rx_EN=1;
      Tx_EN=1;
      Tx_Data=dataToSend[15:8];
      reset=0;
      data_counter = 0 ; 
      
      #5 Tx_WR = 0 ; 
    end
  
  
//explicit port mapping for transmitter and receiver
  uart_transimitter Ut(reset,clk,Tx_Data,wrong_baud_select,Tx_WR,Tx_EN,TxD,Tx_BUSY);
  
  uart_receiver Ur (reset,clk,Rx_DATA,baud_select,Rx_EN,TxD,Rx_FERROR,Rx_PERROR,Rx_VALID);
  
  //clock
  initial begin
    forever begin
      clk<=1;
      #10
      clk<=0;
      #10
      clk <=1;
    end
  end
  
  //system
  initial begin
    #27000 $finish;
  end
    initial
    begin
       $dumpfile("dump.vcd"); $dumpvars;
     
    end
  

  // closing the enable signals after communication
  always #1@(posedge Rx_VALID , posedge Rx_FERROR , posedge Rx_PERROR ) 
    begin 
      Rx_EN <= 0 ; 
      Tx_EN <= 0 ; 
    end
  
  //loading the second data set and starting again the communication
  always @(negedge Rx_EN ) 
    begin 
      data_counter = data_counter + 1; 
      if(data_counter == 1) 
        begin 
          Tx_Data=dataToSend[7:0];
          
          #1000
          
          Tx_EN=1;
           Tx_WR=1;
      	   Rx_EN=1;
           
      	   
      	   reset=0;
          
       		#5 Tx_WR = 0 ; 
          
        end
      
    end 
  
endmodule

code_EDA_files/part2/dump.vcd
$date
	Mon Jan 30 15:58:16 2023
$end
$version
	Icarus Verilog
$end
$timescale
	1ns
$end
$scope module HW2 $end
$var wire 8 ! Rx_DATA [7:0] $end
$var wire 1 " Rx_FERROR $end
$var wire 1 # Rx_PERROR $end
$var wire 1 $ Rx_VALID $end
$var wire 1 % TxD $end
$var wire 1 & Tx_BUSY $end
$var reg 1 ' Rx_EN $end
$var reg 8 ( Tx_Data [7:0] $end
$var reg 1 ) Tx_EN $end
$var reg 1 * Tx_WR $end
$var reg 3 + baud_select [2:0] $end
$var reg 1 , clk $end
$var reg 16 - dataToSend [15:0] $end
$var integer 32 . data_counter [31:0] $end
$var reg 1 / reset $end
$var reg 3 0 wrong_baud_select [2:0] $end
$scope module Ut $end
$var wire 8 1 Tx_Data [7:0] $end
$var wire 1 2 Tx_EN $end
$var wire 1 3 Tx_WR $end
$var wire 1 4 Tx_sample_ENABLE $end
$var wire 3 5 baud_select [2:0] $end
$var wire 1 6 clk $end
$var wire 1 7 reset $end
$var reg 1 8 TxD $end
$var reg 1 9 Tx_BUSY $end
$var reg 1 : current_state $end
$var reg 1 ; next_state $end
$var reg 1 < parity_bit $end
$var reg 4 = tx_counter [3:0] $end
$scope module baud_controller_tx_instance $end
$var wire 3 > baud_select [2:0] $end
$var wire 1 6 clk $end
$var wire 1 7 reset $end
$var reg 16 ? baudCounter [15:0] $end
$var reg 16 @ divisor [15:0] $end
$var reg 1 A sample_ENABLE $end
$upscope $end
$upscope $end
$scope module Ur $end
$var wire 1 % RxD $end
$var wire 1 B Rx_EN $end
$var wire 1 C Rx_sample_ENABLE $end
$var wire 3 D baud_select [2:0] $end
$var wire 1 6 clk $end
$var wire 1 7 reset $end
$var reg 8 E Rx_DATA [7:0] $end
$var reg 1 F Rx_FERROR $end
$var reg 1 G Rx_PERROR $end
$var reg 8 H Rx_POS_DATA [7:0] $end
$var reg 1 I Rx_VALID $end
$var reg 4 J Rx_counter [3:0] $end
$var reg 1 K Rx_parity_bit $end
$var reg 1 L Tx_parity_bit $end
$var reg 1 M current_state $end
$var reg 1 N next_state $end
$var reg 1 O state $end
$scope module baud_controller_rx_instance $end
$var wire 3 P baud_select [2:0] $end
$var wire 1 6 clk $end
$var wire 1 7 reset $end
$var reg 16 Q baudCounter [15:0] $end
$var reg 16 R divisor [15:0] $end
$var reg 1 S sample_ENABLE $end
$upscope $end
$upscope $end
$upscope $end
$enddefinitions $end
#0
$dumpvars
0S
b11011 R
b1 Q
b111 P
0O
1N
1M
0L
0K
b0 J
0I
bx H
0G
0F
b0 E
b111 D
0C
1B
0A
b10100011 @
b1 ?
b100 >
b0 =
0<
1;
0:
09
18
07
16
b100 5
04
13
12
b10101000 1
b100 0
0/
b0 .
b1010100010001000 -
1,
b111 +
1*
1)
b10101000 (
1'
0&
1%
0$
0#
0"
b0 !
$end
#5
0*
03
#10
0,
06
#20
b10 Q
b10 ?
1,
16
#30
0,
06
#40
b11 ?
b11 Q
1,
16
#50
0,
06
#60
b100 Q
b100 ?
1,
16
#70
0,
06
#80
b101 ?
b101 Q
1,
16
#90
0,
06
#100
b110 Q
b110 ?
1,
16
#110
0,
06
#120
b111 ?
b111 Q
1,
16
#130
0,
06
#140
b1000 Q
b1000 ?
1,
16
#150
0,
06
#160
b1001 ?
b1001 Q
1,
16
#170
0,
06
#180
b1010 Q
b1010 ?
1,
16
#190
0,
06
#200
b1011 ?
b1011 Q
1,
16
#210
0,
06
#220
b1100 Q
b1100 ?
1,
16
#230
0,
06
#240
b1101 ?
b1101 Q
1,
16
#250
0,
06
#260
b1110 Q
b1110 ?
1,
16
#270
0,
06
#280
b1111 ?
b1111 Q
1,
16
#290
0,
06
#300
b10000 Q
b10000 ?
1,
16
#310
0,
06
#320
b10001 ?
b10001 Q
1,
16
#330
0,
06
#340
b10010 Q
b10010 ?
1,
16
#350
0,
06
#360
b10011 ?
b10011 Q
1,
16
#370
0,
06
#380
b10100 Q
b10100 ?
1,
16
#390
0,
06
#400
b10101 ?
b10101 Q
1,
16
#410
0,
06
#420
b10110 Q
b10110 ?
1,
16
#430
0,
06
#440
b10111 ?
b10111 Q
1,
16
#450
0,
06
#460
b11000 Q
b11000 ?
1,
16
#470
0,
06
#480
b11001 ?
b11001 Q
1,
16
#490
0,
06
#500
b11010 Q
b11010 ?
1,
16
#510
0,
06
#520
b11011 ?
1S
1C
b0 Q
1,
16
#530
0,
06
#540
b1 Q
b11100 ?
1,
16
#550
0,
06
#560
b11101 ?
b10 Q
1,
16
#570
0,
06
#580
b11 Q
b11110 ?
1,
16
#590
0,
06
#600
b11111 ?
b100 Q
1,
16
#610
0,
06
#620
b101 Q
b100000 ?
1,
16
#630
0,
06
#640
b100001 ?
b110 Q
1,
16
#650
0,
06
#660
b111 Q
b100010 ?
1,
16
#670
0,
06
#680
b100011 ?
b1000 Q
1,
16
#690
0,
06
#700
b1001 Q
b100100 ?
1,
16
#710
0,
06
#720
b100101 ?
b1010 Q
1,
16
#730
0,
06
#740
b1011 Q
b100110 ?
1,
16
#750
0,
06
#760
b100111 ?
b1100 Q
1,
16
#770
0,
06
#780
b1101 Q
b101000 ?
1,
16
#790
0,
06
#800
b101001 ?
b1110 Q
1,
16
#810
0,
06
#820
b1111 Q
b101010 ?
1,
16
#830
0,
06
#840
b101011 ?
b10000 Q
1,
16
#850
0,
06
#860
b10001 Q
b101100 ?
1,
16
#870
0,
06
#880
b101101 ?
b10010 Q
1,
16
#890
0,
06
#900
b10011 Q
b101110 ?
1,
16
#910
0,
06
#920
b101111 ?
b10100 Q
1,
16
#930
0,
06
#940
b10101 Q
b110000 ?
1,
16
#950
0,
06
#960
b110001 ?
b10110 Q
1,
16
#970
0,
06
#980
b10111 Q
b110010 ?
1,
16
#990
0,
06
#1000
b110011 ?
b11000 Q
1,
16
#1010
0,
06
#1020
b11001 Q
b110100 ?
1,
16
#1030
0,
06
#1040
b110101 ?
b11010 Q
1,
16
#1050
0,
06
#1060
0S
0C
b0 Q
b110110 ?
1,
16
#1070
0,
06
#1080
b110111 ?
b1 Q
1,
16
#1090
0,
06
#1100
b10 Q
b111000 ?
1,
16
#1110
0,
06
#1120
b111001 ?
b11 Q
1,
16
#1130
0,
06
#1140
b100 Q
b111010 ?
1,
16
#1150
0,
06
#1160
b111011 ?
b101 Q
1,
16
#1170
0,
06
#1180
b110 Q
b111100 ?
1,
16
#1190
0,
06
#1200
b111101 ?
b111 Q
1,
16
#1210
0,
06
#1220
b1000 Q
b111110 ?
1,
16
#1230
0,
06
#1240
b111111 ?
b1001 Q
1,
16
#1250
0,
06
#1260
b1010 Q
b1000000 ?
1,
16
#1270
0,
06
#1280
b1000001 ?
b1011 Q
1,
16
#1290
0,
06
#1300
b1100 Q
b1000010 ?
1,
16
#1310
0,
06
#1320
b1000011 ?
b1101 Q
1,
16
#1330
0,
06
#1340
b1110 Q
b1000100 ?
1,
16
#1350
0,
06
#1360
b1000101 ?
b1111 Q
1,
16
#1370
0,
06
#1380
b10000 Q
b1000110 ?
1,
16
#1390
0,
06
#1400
b1000111 ?
b10001 Q
1,
16
#1410
0,
06
#1420
b10010 Q
b1001000 ?
1,
16
#1430
0,
06
#1440
b1001001 ?
b10011 Q
1,
16
#1450
0,
06
#1460
b10100 Q
b1001010 ?
1,
16
#1470
0,
06
#1480
b1001011 ?
b10101 Q
1,
16
#1490
0,
06
#1500
b10110 Q
b1001100 ?
1,
16
#1510
0,
06
#1520
b1001101 ?
b10111 Q
1,
16
#1530
0,
06
#1540
b11000 Q
b1001110 ?
1,
16
#1550
0,
06
#1560
b1001111 ?
b11001 Q
1,
16
#1570
0,
06
#1580
b11010 Q
b1010000 ?
1,
16
#1590
0,
06
#1600
b1010001 ?
1S
1C
b0 Q
1,
16
#1610
0,
06
#1620
b1 Q
b1010010 ?
1,
16
#1630
0,
06
#1640
b1010011 ?
b10 Q
1,
16
#1650
0,
06
#1660
b11 Q
b1010100 ?
1,
16
#1670
0,
06
#1680
b1010101 ?
b100 Q
1,
16
#1690
0,
06
#1700
b101 Q
b1010110 ?
1,
16
#1710
0,
06
#1720
b1010111 ?
b110 Q
1,
16
#1730
0,
06
#1740
b111 Q
b1011000 ?
1,
16
#1750
0,
06
#1760
b1011001 ?
b1000 Q
1,
16
#1770
0,
06
#1780
b1001 Q
b1011010 ?
1,
16
#1790
0,
06
#1800
b1011011 ?
b1010 Q
1,
16
#1810
0,
06
#1820
b1011 Q
b1011100 ?
1,
16
#1830
0,
06
#1840
b1011101 ?
b1100 Q
1,
16
#1850
0,
06
#1860
b1101 Q
b1011110 ?
1,
16
#1870
0,
06
#1880
b1011111 ?
b1110 Q
1,
16
#1890
0,
06
#1900
b1111 Q
b1100000 ?
1,
16
#1910
0,
06
#1920
b1100001 ?
b10000 Q
1,
16
#1930
0,
06
#1940
b10001 Q
b1100010 ?
1,
16
#1950
0,
06
#1960
b1100011 ?
b10010 Q
1,
16
#1970
0,
06
#1980
b10011 Q
b1100100 ?
1,
16
#1990
0,
06
#2000
b1100101 ?
b10100 Q
1,
16
#2010
0,
06
#2020
b10101 Q
b1100110 ?
1,
16
#2030
0,
06
#2040
b1100111 ?
b10110 Q
1,
16
#2050
0,
06
#2060
b10111 Q
b1101000 ?
1,
16
#2070
0,
06
#2080
b1101001 ?
b11000 Q
1,
16
#2090
0,
06
#2100
b11001 Q
b1101010 ?
1,
16
#2110
0,
06
#2120
b1101011 ?
b11010 Q
1,
16
#2130
0,
06
#2140
0S
0C
b0 Q
b1101100 ?
1,
16
#2150
0,
06
#2160
b1101101 ?
b1 Q
1,
16
#2170
0,
06
#2180
b10 Q
b1101110 ?
1,
16
#2190
0,
06
#2200
b1101111 ?
b11 Q
1,
16
#2210
0,
06
#2220
b100 Q
b1110000 ?
1,
16
#2230
0,
06
#2240
b1110001 ?
b101 Q
1,
16
#2250
0,
06
#2260
b110 Q
b1110010 ?
1,
16
#2270
0,
06
#2280
b1110011 ?
b111 Q
1,
16
#2290
0,
06
#2300
b1000 Q
b1110100 ?
1,
16
#2310
0,
06
#2320
b1110101 ?
b1001 Q
1,
16
#2330
0,
06
#2340
b1010 Q
b1110110 ?
1,
16
#2350
0,
06
#2360
b1110111 ?
b1011 Q
1,
16
#2370
0,
06
#2380
b1100 Q
b1111000 ?
1,
16
#2390
0,
06
#2400
b1111001 ?
b1101 Q
1,
16
#2410
0,
06
#2420
b1110 Q
b1111010 ?
1,
16
#2430
0,
06
#2440
b1111011 ?
b1111 Q
1,
16
#2450
0,
06
#2460
b10000 Q
b1111100 ?
1,
16
#2470
0,
06
#2480
b1111101 ?
b10001 Q
1,
16
#2490
0,
06
#2500
b10010 Q
b1111110 ?
1,
16
#2510
0,
06
#2520
b1111111 ?
b10011 Q
1,
16
#2530
0,
06
#2540
b10100 Q
b10000000 ?
1,
16
#2550
0,
06
#2560
b10000001 ?
b10101 Q
1,
16
#2570
0,
06
#2580
b10110 Q
b10000010 ?
1,
16
#2590
0,
06
#2600
b10000011 ?
b10111 Q
1,
16
#2610
0,
06
#2620
b11000 Q
b10000100 ?
1,
16
#2630
0,
06
#2640
b10000101 ?
b11001 Q
1,
16
#2650
0,
06
#2660
b11010 Q
b10000110 ?
1,
16
#2670
0,
06
#2680
b10000111 ?
1S
1C
b0 Q
1,
16
#2690
0,
06
#2700
b1 Q
b10001000 ?
1,
16
#2710
0,
06
#2720
b10001001 ?
b10 Q
1,
16
#2730
0,
06
#2740
b11 Q
b10001010 ?
1,
16
#2750
0,
06
#2760
b10001011 ?
b100 Q
1,
16
#2770
0,
06
#2780
b101 Q
b10001100 ?
1,
16
#2790
0,
06
#2800
b10001101 ?
b110 Q
1,
16
#2810
0,
06
#2820
b111 Q
b10001110 ?
1,
16
#2830
0,
06
#2840
b10001111 ?
b1000 Q
1,
16
#2850
0,
06
#2860
b1001 Q
b10010000 ?
1,
16
#2870
0,
06
#2880
b10010001 ?
b1010 Q
1,
16
#2890
0,
06
#2900
b1011 Q
b10010010 ?
1,
16
#2910
0,
06
#2920
b10010011 ?
b1100 Q
1,
16
#2930
0,
06
#2940
b1101 Q
b10010100 ?
1,
16
#2950
0,
06
#2960
b10010101 ?
b1110 Q
1,
16
#2970
0,
06
#2980
b1111 Q
b10010110 ?
1,
16
#2990
0,
06
#3000
b10010111 ?
b10000 Q
1,
16
#3010
0,
06
#3020
b10001 Q
b10011000 ?
1,
16
#3030
0,
06
#3040
b10011001 ?
b10010 Q
1,
16
#3050
0,
06
#3060
b10011 Q
b10011010 ?
1,
16
#3070
0,
06
#3080
b10011011 ?
b10100 Q
1,
16
#3090
0,
06
#3100
b10101 Q
b10011100 ?
1,
16
#3110
0,
06
#3120
b10011101 ?
b10110 Q
1,
16
#3130
0,
06
#3140
b10111 Q
b10011110 ?
1,
16
#3150
0,
06
#3160
b10011111 ?
b11000 Q
1,
16
#3170
0,
06
#3180
b11001 Q
b10100000 ?
1,
16
#3190
0,
06
#3200
b10100001 ?
b11010 Q
1,
16
#3210
0,
06
#3220
0S
0C
b0 Q
b10100010 ?
1,
16
#3230
0,
06
#3240
0;
0N
b10001000 (
b10001000 1
b1 .
0)
02
0'
0B
1F
1"
b1 =
08
0%
19
1&
1:
1A
14
b0 ?
b1 Q
1,
16
#3250
0,
06
#3260
b10 Q
b1 ?
1,
16
#3270
0,
06
#3280
b10 ?
b11 Q
1,
16
#3290
0,
06
#3300
b100 Q
b11 ?
1,
16
#3310
0,
06
#3320
b100 ?
b101 Q
1,
16
#3330
0,
06
#3340
b110 Q
b101 ?
1,
16
#3350
0,
06
#3360
b110 ?
b111 Q
1,
16
#3370
0,
06
#3380
b1000 Q
b111 ?
1,
16
#3390
0,
06
#3400
b1000 ?
b1001 Q
1,
16
#3410
0,
06
#3420
b1010 Q
b1001 ?
1,
16
#3430
0,
06
#3440
b1010 ?
b1011 Q
1,
16
#3450
0,
06
#3460
b1100 Q
b1011 ?
1,
16
#3470
0,
06
#3480
b1100 ?
b1101 Q
1,
16
#3490
0,
06
#3500
b1110 Q
b1101 ?
1,
16
#3510
0,
06
#3520
b1110 ?
b1111 Q
1,
16
#3530
0,
06
#3540
b10000 Q
b1111 ?
1,
16
#3550
0,
06
#3560
b10000 ?
b10001 Q
1,
16
#3570
0,
06
#3580
b10010 Q
b10001 ?
1,
16
#3590
0,
06
#3600
b10010 ?
b10011 Q
1,
16
#3610
0,
06
#3620
b10100 Q
b10011 ?
1,
16
#3630
0,
06
#3640
b10100 ?
b10101 Q
1,
16
#3650
0,
06
#3660
b10110 Q
b10101 ?
1,
16
#3670
0,
06
#3680
b10110 ?
b10111 Q
1,
16
#3690
0,
06
#3700
b11000 Q
b10111 ?
1,
16
#3710
0,
06
#3720
b11000 ?
b11001 Q
1,
16
#3730
0,
06
#3740
b11010 Q
b11001 ?
1,
16
#3750
0,
06
#3760
b11010 ?
1S
1C
b0 Q
1,
16
#3770
0,
06
#3780
b1 Q
b11011 ?
1,
16
#3790
0,
06
#3800
b11100 ?
b10 Q
1,
16
#3810
0,
06
#3820
b11 Q
b11101 ?
1,
16
#3830
0,
06
#3840
b11110 ?
b100 Q
1,
16
#3850
0,
06
#3860
b101 Q
b11111 ?
1,
16
#3870
0,
06
#3880
b100000 ?
b110 Q
1,
16
#3890
0,
06
#3900
b111 Q
b100001 ?
1,
16
#3910
0,
06
#3920
b100010 ?
b1000 Q
1,
16
#3930
0,
06
#3940
b1001 Q
b100011 ?
1,
16
#3950
0,
06
#3960
b100100 ?
b1010 Q
1,
16
#3970
0,
06
#3980
b1011 Q
b100101 ?
1,
16
#3990
0,
06
#4000
b100110 ?
b1100 Q
1,
16
#4010
0,
06
#4020
b1101 Q
b100111 ?
1,
16
#4030
0,
06
#4040
b101000 ?
b1110 Q
1,
16
#4050
0,
06
#4060
b1111 Q
b101001 ?
1,
16
#4070
0,
06
#4080
b101010 ?
b10000 Q
1,
16
#4090
0,
06
#4100
b10001 Q
b101011 ?
1,
16
#4110
0,
06
#4120
b101100 ?
b10010 Q
1,
16
#4130
0,
06
#4140
b10011 Q
b101101 ?
1,
16
#4150
0,
06
#4160
b101110 ?
b10100 Q
1,
16
#4170
0,
06
#4180
b10101 Q
b101111 ?
1,
16
#4190
0,
06
#4200
b110000 ?
b10110 Q
1,
16
#4210
0,
06
#4220
b10111 Q
b110001 ?
1,
16
#4230
0,
06
#4240
b110010 ?
b11000 Q
1N
0F
0"
0:
18
1%
b0 =
09
0&
0;
1,
16
1'
1B
1*
13
1)
12
#4245
0*
03
#4250
0,
06
#4260
b11001 Q
b110011 ?
1,
16
#4270
0,
06
#4280
b110100 ?
b11010 Q
1,
16
#4290
0,
06
#4300
0S
0C
b0 Q
b110101 ?
1,
16
#4310
0,
06
#4320
b110110 ?
b1 Q
1,
16
#4330
0,
06
#4340
b10 Q
b110111 ?
1,
16
#4350
0,
06
#4360
b111000 ?
b11 Q
1,
16
#4370
0,
06
#4380
b100 Q
b111001 ?
1,
16
#4390
0,
06
#4400
b111010 ?
b101 Q
1,
16
#4410
0,
06
#4420
b110 Q
b111011 ?
1,
16
#4430
0,
06
#4440
b111100 ?
b111 Q
1,
16
#4450
0,
06
#4460
b1000 Q
b111101 ?
1,
16
#4470
0,
06
#4480
b111110 ?
b1001 Q
1,
16
#4490
0,
06
#4500
b1010 Q
b111111 ?
1,
16
#4510
0,
06
#4520
b1000000 ?
b1011 Q
1,
16
#4530
0,
06
#4540
b1100 Q
b1000001 ?
1,
16
#4550
0,
06
#4560
b1000010 ?
b1101 Q
1,
16
#4570
0,
06
#4580
b1110 Q
b1000011 ?
1,
16
#4590
0,
06
#4600
b1000100 ?
b1111 Q
1,
16
#4610
0,
06
#4620
b10000 Q
b1000101 ?
1,
16
#4630
0,
06
#4640
b1000110 ?
b10001 Q
1,
16
#4650
0,
06
#4660
b10010 Q
b1000111 ?
1,
16
#4670
0,
06
#4680
b1001000 ?
b10011 Q
1,
16
#4690
0,
06
#4700
b10100 Q
b1001001 ?
1,
16
#4710
0,
06
#4720
b1001010 ?
b10101 Q
1,
16
#4730
0,
06
#4740
b10110 Q
b1001011 ?
1,
16
#4750
0,
06
#4760
b1001100 ?
b10111 Q
1,
16
#4770
0,
06
#4780
b11000 Q
b1001101 ?
1,
16
#4790
0,
06
#4800
b1001110 ?
b11001 Q
1,
16
#4810
0,
06
#4820
b11010 Q
b1001111 ?
1,
16
#4830
0,
06
#4840
b1010000 ?
1S
1C
b0 Q
1,
16
#4850
0,
06
#4860
b1 Q
b1010001 ?
1,
16
#4870
0,
06
#4880
b1010010 ?
b10 Q
1,
16
#4890
0,
06
#4900
b11 Q
b1010011 ?
1,
16
#4910
0,
06
#4920
b1010100 ?
b100 Q
1,
16
#4930
0,
06
#4940
b101 Q
b1010101 ?
1,
16
#4950
0,
06
#4960
b1010110 ?
b110 Q
1,
16
#4970
0,
06
#4980
b111 Q
b1010111 ?
1,
16
#4990
0,
06
#5000
b1011000 ?
b1000 Q
1,
16
#5010
0,
06
#5020
b1001 Q
b1011001 ?
1,
16
#5030
0,
06
#5040
b1011010 ?
b1010 Q
1,
16
#5050
0,
06
#5060
b1011 Q
b1011011 ?
1,
16
#5070
0,
06
#5080
b1011100 ?
b1100 Q
1,
16
#5090
0,
06
#5100
b1101 Q
b1011101 ?
1,
16
#5110
0,
06
#5120
b1011110 ?
b1110 Q
1,
16
#5130
0,
06
#5140
b1111 Q
b1011111 ?
1,
16
#5150
0,
06
#5160
b1100000 ?
b10000 Q
1,
16
#5170
0,
06
#5180
b10001 Q
b1100001 ?
1,
16
#5190
0,
06
#5200
b1100010 ?
b10010 Q
1,
16
#5210
0,
06
#5220
b10011 Q
b1100011 ?
1,
16
#5230
0,
06
#5240
b1100100 ?
b10100 Q
1,
16
#5250
0,
06
#5260
b10101 Q
b1100101 ?
1,
16
#5270
0,
06
#5280
b1100110 ?
b10110 Q
1,
16
#5290
0,
06
#5300
b10111 Q
b1100111 ?
1,
16
#5310
0,
06
#5320
b1101000 ?
b11000 Q
1,
16
#5330
0,
06
#5340
b11001 Q
b1101001 ?
1,
16
#5350
0,
06
#5360
b1101010 ?
b11010 Q
1,
16
#5370
0,
06
#5380
0S
0C
b0 Q
b1101011 ?
1,
16
#5390
0,
06
#5400
b1101100 ?
b1 Q
1,
16
#5410
0,
06
#5420
b10 Q
b1101101 ?
1,
16
#5430
0,
06
#5440
b1101110 ?
b11 Q
1,
16
#5450
0,
06
#5460
b100 Q
b1101111 ?
1,
16
#5470
0,
06
#5480
b1110000 ?
b101 Q
1,
16
#5490
0,
06
#5500
b110 Q
b1110001 ?
1,
16
#5510
0,
06
#5520
b1110010 ?
b111 Q
1,
16
#5530
0,
06
#5540
b1000 Q
b1110011 ?
1,
16
#5550
0,
06
#5560
b1110100 ?
b1001 Q
1,
16
#5570
0,
06
#5580
b1010 Q
b1110101 ?
1,
16
#5590
0,
06
#5600
b1110110 ?
b1011 Q
1,
16
#5610
0,
06
#5620
b1100 Q
b1110111 ?
1,
16
#5630
0,
06
#5640
b1111000 ?
b1101 Q
1,
16
#5650
0,
06
#5660
b1110 Q
b1111001 ?
1,
16
#5670
0,
06
#5680
b1111010 ?
b1111 Q
1,
16
#5690
0,
06
