code_EDA_files/part3/design.sv
`timescale 1ns/1ns

module baud_controller(reset, clk, baud_select, sample_ENABLE);
  input wire clk,reset;
  input wire [2:0] baud_select;
  output reg sample_ENABLE;
  
  reg [2:0] baudRate;
  reg [15:0] divisor;
  reg [15:0] baudCounter;
  
  initial
    begin
          baudCounter<=0;
          sample_ENABLE<=0;
    end
  
  always @(baud_select)
  begin
    case(baud_select)
      3'b000: divisor=16'd10417;
      3'b001: divisor=16'd2604;
      3'b010: divisor=16'd651;
      3'b011: divisor=16'd326;
      3'b100: divisor=16'd163;
      3'b101: divisor=16'd81;
      3'b110: divisor=16'd54;
      3'b111: divisor=16'd27;
    endcase
  end
  
  always @(posedge clk)
    begin
      if(reset)
        begin
          baudCounter<=0;
          sample_ENABLE<=0;
        end
      else
        begin
          baudCounter<=baudCounter+1;
          if(baudCounter==(divisor-1))
            begin
              sample_ENABLE<=~sample_ENABLE;
              baudCounter<=0;
             
            end     
        end
    end
endmodule


//------------------------------------------------------------



module uart_transimitter(reset,clk,Tx_Data,baud_select,Tx_WR,Tx_EN,TxD,Tx_BUSY);
  input wire reset;
  input wire clk;
  input wire [7:0] Tx_Data;
  input wire [2:0] baud_select;
  input wire Tx_WR;
  input wire Tx_EN;
  output reg TxD;
  output reg Tx_BUSY;
  
  wire Tx_sample_ENABLE;
  
  reg [3:0] tx_counter;
  reg parity_bit;
  integer i;

   
  reg current_state, next_state ; 
  parameter tx_on = 1'b1 ,
  			 tx_off = 1'b0 ; 
  
  			 
  
  baud_controller baud_controller_tx_instance(reset,clk,baud_select,Tx_sample_ENABLE);
  

  initial 
    begin
     Tx_BUSY<=0;
     tx_counter<=0;
     TxD<=1;
     current_state <= tx_off ; 
     next_state <= tx_off ; 
     parity_bit<=0; 
      
      
    end 
  
  always @(posedge Tx_WR) 
    begin 
      Tx_BUSY<=0;
      tx_counter<=0;
      TxD<=1;
      current_state <= tx_off ; 
      next_state <= tx_off ; 
      parity_bit<=0; 
    end 
  
  
  always @(posedge Tx_sample_ENABLE)
    begin
      if(reset)
        begin
          Tx_BUSY<=0;
          tx_counter<=0;
          TxD<=1;
          current_state <= tx_off ; 
          next_state <= tx_off ; 
          parity_bit<=0;
          
          
        end
      else
        begin
          current_state <= next_state ; 
          if(Tx_EN )
            begin
             
                  Tx_BUSY<=1;
                  
                  if(tx_counter==0)
                    TxD<=1'b0; //start bit
                  else if (tx_counter==10)
                   	TxD<=1'b0; //stop bit
                  else if (tx_counter==9)
                    TxD<=parity_bit;
                  else 
                    begin
                      TxD<=Tx_Data[tx_counter-1];
                      
                      if(Tx_Data[tx_counter-1])
                         if(parity_bit)
                            parity_bit<=0;
                        else
                          parity_bit<=1;
                      
                    end
                  
                  
                   tx_counter<= tx_counter+1;
                  if(tx_counter==11)
                    begin
                      	Tx_BUSY<=0;
                      	TxD<=1;

                      
                    end
                  
                end          

                      
        end     
    end
  
  always @(Tx_EN) 
    begin 
      if( Tx_EN == 1) 
        next_state <= tx_on ; 
      else 
        next_state <= tx_off; 
    end 

endmodule
//------------------------------------------------------------

module uart_receiver (reset,clk,Rx_DATA,baud_select,Rx_EN,RxD,Rx_FERROR,Rx_PERROR,Rx_VALID);
  input wire  reset,clk;
  input wire [2:0] baud_select;
  input wire Rx_EN;
  input wire RxD;
  
  output reg [7:0] Rx_DATA;
  output reg Rx_FERROR;
  output reg Rx_PERROR; 
  output reg Rx_VALID;
  
  wire Rx_sample_ENABLE;
  
  reg [3:0] Rx_counter;
  reg Rx_parity_bit;
  reg Tx_parity_bit;
  reg state;
  reg [7:0] Rx_POS_DATA;


  
  integer i;
  
  reg current_state, next_state ; 
  parameter rx_on = 1'b1 ,
  			 rx_off = 1'b0 ; 
  
  baud_controller baud_controller_rx_instance(reset,clk,baud_select,Rx_sample_ENABLE);
  
  initial 
    begin
      
       Rx_counter<=0;
       Rx_FERROR<=0;
       Rx_PERROR<=0; 
       Rx_VALID<=0;
       state<=0;
       Rx_DATA <= 0 ; 
      current_state <= rx_off ; 
      next_state <= rx_off ; 
      Tx_parity_bit<= 0 ;
       Rx_parity_bit <= 0 ; 
    end 
  
 
  
  
  always  @(negedge RxD)
    begin
      if (Rx_sample_ENABLE==0)
        Rx_FERROR=1;
        
    end
  
  always @(posedge Rx_EN) 
    begin 
        Rx_counter<=0;
        state<=0;
        Rx_FERROR<=0;
        Rx_PERROR<=0;
      	Rx_VALID <= 0; 
        Tx_parity_bit<= 0 ;
        Rx_parity_bit <= 0 ; 
      
    end 
  
  
   
  always @(negedge Rx_sample_ENABLE)
  begin
      if(reset)
        begin
          Rx_counter<=0;
          Rx_FERROR<=0;
          Rx_PERROR<=0; 
          Rx_VALID<=0;
          state<=0;
          Rx_DATA <= 0 ;
          current_state <= rx_off ; 
     	  next_state <= rx_off ; 
          Tx_parity_bit<= 0 ;
          Rx_parity_bit <= 0 ; 
          
          

        end
      else
        begin
          current_state <= next_state ; 
          if(Rx_EN)
           begin
            if(!RxD && !state)
              begin
                state<=1;
                Rx_counter<=Rx_counter+1;
                Rx_VALID<=0;
                Rx_parity_bit<=0;
              end
            else if (state)
              begin
                if (Rx_counter<9)
                  begin
                    Rx_POS_DATA[Rx_counter-1]<=RxD;
                    Rx_counter<=Rx_counter+1;
                    
                    if(RxD)
                          if(Rx_parity_bit)
                            Rx_parity_bit<=0;
                        else
                          Rx_parity_bit<=1;
                  end
                else if (Rx_counter==9)
                  begin
                    Tx_parity_bit =RxD;
                    
                    Rx_counter<=Rx_counter+1;
                      
                    
                    if (Rx_parity_bit!=Tx_parity_bit)
                      Rx_PERROR<=1;

                  end
                else if (Rx_counter==10)
                  begin

                    if(!Rx_PERROR && !Rx_FERROR)
                      begin
                        Rx_VALID<=1;
                        Rx_DATA<=Rx_POS_DATA;

                      end



                  end



                  






              end	//state




          end //enable
    	end //else of reset
        
      
    end	//always block
  
  

  always @(Rx_EN) 
    begin 
      if( Rx_EN == 1) 
        next_state <= rx_on ; 
      else 
        next_state <= rx_off; 
    end 


endmodule
//------------------------------------------------------------

//MODULE THAT MAKES PART2 OUTPUT SUITABLE FOR PART1 INPUT 
module messageDisp(clk,Rx_DATA,Rx_FERROR,Rx_PERROR,Rx_VALID,myChar0,myChar1,myChar2,myChar3,dispReady,setReady);
    input wire [7:0] Rx_DATA;
    input wire Rx_FERROR;
    input wire Rx_PERROR;
    input wire Rx_VALID;
  	input wire clk;
  
  	output reg [3:0] myChar0;
  	output reg [3:0] myChar1;
  	output reg [3:0] myChar2;
  	output reg [3:0] myChar3;
  	output reg dispReady;
  	output reg setReady;
    
    reg set;
    reg Valid1, Valid2;
  	
  reg [1:0] current_state,next_state;
  	parameter w_idle=2'b00,
  			w_set1=2'b01,
  			w_set2=2'b10;
  
  	initial
      begin

        dispReady=0;
        setReady=0;
        
        set=0;
        Valid1=0;
        Valid2=0;
        current_state= w_idle;
        next_state= w_idle;
        
      end
  
  always @(posedge clk)
    begin
      current_state=next_state;
    end
  
  always @(posedge Rx_VALID , posedge Rx_FERROR , posedge Rx_PERROR ) 
    begin
      
      if(set==0)
        begin
          //for 1st 8-bit set
          Valid1 =  Rx_VALID ;
          myChar3=Rx_DATA[7:4];
          myChar2=Rx_DATA[3:0];
          setReady=1;
          dispReady=0;
          set=1;
        end
      else
        begin
          //for 2nd 8-bit set
          Valid2 =  Rx_VALID ;
          myChar1=Rx_DATA[7:4];
          myChar0=Rx_DATA[3:0];
          
          //checks if all the bits have been received correct
          if(Valid1==0 || Valid2==0 ) 
            begin 
              //if there is an error we display FFFF
              myChar0=4'b1011 ; 
              myChar1=4'b1011 ; 
              myChar2=4'b1011 ; 
              myChar3=4'b1011 ; 
            end
          dispReady=1;
          setReady=0;
          set=0;
        end
      
      
    end
  
  //fsm
  always @(set)
    begin
      if (set==0)
        next_state=w_set1;
      else
        next_state=w_set2;
      
    end



endmodule

//------------------------------------------------------------
  module LEDcoder( char, LED);
    input wire[3:0] char;
    output reg [7:0] LED;
    
    
    always @ (char)
      begin
 
        case(char) 
          4'b0000 : LED[7:0] <= 8'b00000011 ; 
          4'b0001 : LED[7:0] <= 8'b10011111 ; 
          4'b0010 : LED[7:0] <= 8'b00100101 ; 
          4'b0011 : LED[7:0] <= 8'b00001101 ; 
          4'b0100 : LED[7:0] <= 8'b10011001 ; 
          4'b0101 : LED[7:0] <= 8'b01001001 ; 
          4'b0110 : LED[7:0] <= 8'b01000001 ; 
          4'b0111 : LED[7:0] <= 8'b00011111 ; 
          4'b1000 : LED[7:0] <= 8'b00000001 ; 
          4'b1001 : LED[7:0] <= 8'b00001001 ; 
          4'b1010 : LED[7:0] <= 8'b11111101 ; 
          4'b1011 : LED[7:0] <= 8'b01110001 ; 
          4'b1100 : LED[7:0] <= 8'b11111111 ; 
        
        endcase 
    	      
	      
      end
      
  endmodule
//------------------------------------------------------------

module anodoi(clk,HEX3,HEX2,HEX1,HEX0,AN3,AN2,AN1,AN0,myHex,readyAnodes);
  input wire clk;
  input wire [7:0] HEX3,HEX2,HEX1,HEX0;
  //signal to start the module after the values are ready
  input wire readyAnodes; 
  
  output reg [7:0] myHex;
  output reg AN3,AN2,AN1,AN0;

  
  integer cycles;
  
  //inmplement of fsm
  reg [2:0] current_state, next_state;
  parameter w_closed=3'b100,
  			w_openAN3=3'b011,
  			w_openAN2=3'b010, 
  			w_openAN1=3'b001,
  			w_openAN0=3'b000;
  

    initial
    begin
      AN0=1;
      AN1=1;
      AN2=1;
      AN3=1;
      myHex=0;
      cycles=15;
      current_state=w_closed;
      next_state=w_closed;
    end
  
  
  always @(posedge clk)
    begin
      current_state=next_state;
      
      if (readyAnodes)
        begin
      
       if (cycles==15)
        begin
          cycles=0;
        end
      else
        cycles=cycles+1;
      
      //operation for anodes
       case (cycles)
            4'h2: AN3=0;
            4'h3: AN3=1;
            4'h6: AN2=0;
            4'h7: AN2=1;
            4'hA: AN1=0;
            4'hB: AN1=1;
            4'hE: AN0=0;
            4'hF: AN0=1;

            4'h0:myHex=HEX3;
            4'h4:myHex=HEX2;
            4'h8:myHex=HEX1;
            4'hC:myHex=HEX0;


          endcase
          
        end

    end
  
  always @(AN3,AN2,AN1,AN0)
    begin
      if (AN3==0)
        next_state=w_openAN3;
      else if (AN2==0)
        next_state=w_openAN2;
      else if (AN1==0)
        next_state=w_openAN1;
      else if (AN0==0)
        next_state=w_openAN0;
      else
        next_state=w_closed;
      
    end
 
endmodule

code_EDA_files/part3/testbench.sv
`timescale 1ns/1ns

module HWpart3;
  
  //signals for coordination
  wire setReady;
  wire dispReady;

  reg clk;
  reg [2:0] baud_select;
  reg [2:0] wrong_baud_select;
  reg reset;
  reg [7:0] Tx_Data;
  reg Tx_WR;
  reg Tx_EN;
  reg Rx_EN;
  reg [15:0] dataToSend;

  wire TxD;
  wire Tx_BUSY;
  
  wire [7:0] Rx_DATA;
  wire Rx_FERROR;
  wire Rx_PERROR; 
  wire Rx_VALID;
  
  integer data_counter ; 
  
  
  wire sample_ENABLE;
  

  integer cycles;

  
  wire AN3;
  wire AN2;
  wire AN1;
  wire AN0;
 
  
  wire [3:0] myChar0;
  wire [3:0] myChar1;
  wire [3:0] myChar2;
  wire [3:0] myChar3;
  
  wire [7:0] HEX0 ; 
  wire [7:0] HEX1 ; 
  wire [7:0] HEX2 ; 
  wire [7:0] HEX3 ; 
  
  wire [7:0] myHex;   
  
  //explicit port mapping for transmitter and receiver
  LEDcoder disp0(myChar0, HEX0);
  LEDcoder disp1(myChar1, HEX1);
  LEDcoder disp2(myChar2, HEX2);
  LEDcoder disp3(myChar3, HEX3);
  anodoi Uo(clk,HEX3,HEX2,HEX1,HEX0,AN3,AN2,AN1,AN0,myHex,dispReady);
  
  messageDisp mess(clk,Rx_DATA,Rx_FERROR,Rx_PERROR,Rx_VALID,myChar0,myChar1,myChar2,myChar3,dispReady,setReady);
  

  
  initial
    begin
      dataToSend=16'b1010000110010100;
      
      baud_select=3'b111;
      wrong_baud_select=3'b100;
      Tx_WR=1;
      Rx_EN=1;
      Tx_EN=1;
      Tx_Data=dataToSend[15:8];
      reset=0;
      
      #5 Tx_WR = 0 ; 
    end
	
  uart_transimitter Ut(reset,clk,Tx_Data,baud_select,Tx_WR,Tx_EN,TxD,Tx_BUSY);
  
  uart_receiver Ur (reset,clk,Rx_DATA,baud_select,Rx_EN,TxD,Rx_FERROR,Rx_PERROR,Rx_VALID);
  
  
  
  initial
    begin
       $dumpfile("dump.vcd"); $dumpvars;
     
    end

  initial begin
    forever begin
      clk<=1;
      #10
      clk<=0;
      #10
      clk <=1;
    end
  end
  initial begin
    #40000 $finish;
  end
  
  //after first set
  always @(posedge setReady) 
    begin
      //stop the communication process
      Rx_EN <= 0 ; 
      Tx_EN <= 0 ; 
          
      Tx_Data=dataToSend[7:0]; //load data for second set
      //restart the communication process
      #10
      Tx_EN<=1;
      Tx_WR<=1;
      Rx_EN<=1;
          
      #5 
      Tx_WR <= 0 ;
      
    end 
//after second set
  always @(posedge dispReady) 
    begin 
      //stop the communication process
      Rx_EN <= 0 ; 
      Tx_EN <= 0 ;      
    end 
  
  endmodule

code_EDA_files/part3/dump.vcd
$date
	Mon Jan 30 15:58:54 2023
$end
$version
	Icarus Verilog
$end
$timescale
	1ns
$end
$scope module HWpart3 $end
$var wire 1 ! AN0 $end
$var wire 1 " AN1 $end
$var wire 1 # AN2 $end
$var wire 1 $ AN3 $end
$var wire 8 % HEX0 [7:0] $end
$var wire 8 & HEX1 [7:0] $end
$var wire 8 ' HEX2 [7:0] $end
$var wire 8 ( HEX3 [7:0] $end
$var wire 8 ) Rx_DATA [7:0] $end
$var wire 1 * Rx_FERROR $end
$var wire 1 + Rx_PERROR $end
$var wire 1 , Rx_VALID $end
$var wire 1 - TxD $end
$var wire 1 . Tx_BUSY $end
$var wire 1 / dispReady $end
$var wire 4 0 myChar0 [3:0] $end
$var wire 4 1 myChar1 [3:0] $end
$var wire 4 2 myChar2 [3:0] $end
$var wire 4 3 myChar3 [3:0] $end
$var wire 8 4 myHex [7:0] $end
$var wire 1 5 setReady $end
$var reg 1 6 Rx_EN $end
$var reg 8 7 Tx_Data [7:0] $end
$var reg 1 8 Tx_EN $end
$var reg 1 9 Tx_WR $end
$var reg 3 : baud_select [2:0] $end
$var reg 1 ; clk $end
$var reg 16 < dataToSend [15:0] $end
$var reg 1 = reset $end
$var reg 3 > wrong_baud_select [2:0] $end
$scope module disp0 $end
$var wire 4 ? char [3:0] $end
$var reg 8 @ LED [7:0] $end
$upscope $end
$scope module disp1 $end
$var wire 4 A char [3:0] $end
$var reg 8 B LED [7:0] $end
$upscope $end
$scope module disp2 $end
$var wire 4 C char [3:0] $end
$var reg 8 D LED [7:0] $end
$upscope $end
$scope module disp3 $end
$var wire 4 E char [3:0] $end
$var reg 8 F LED [7:0] $end
$upscope $end
$scope module Uo $end
$var wire 8 G HEX0 [7:0] $end
$var wire 8 H HEX1 [7:0] $end
$var wire 8 I HEX2 [7:0] $end
$var wire 8 J HEX3 [7:0] $end
$var wire 1 K clk $end
$var wire 1 / readyAnodes $end
$var reg 1 L AN0 $end
$var reg 1 M AN1 $end
$var reg 1 N AN2 $end
$var reg 1 O AN3 $end
$var reg 3 P current_state [2:0] $end
$var integer 32 Q cycles [31:0] $end
$var reg 8 R myHex [7:0] $end
$var reg 3 S next_state [2:0] $end
$upscope $end
$scope module mess $end
$var wire 8 T Rx_DATA [7:0] $end
$var wire 1 * Rx_FERROR $end
$var wire 1 + Rx_PERROR $end
$var wire 1 , Rx_VALID $end
$var wire 1 K clk $end
$var reg 1 U Valid1 $end
$var reg 1 V Valid2 $end
$var reg 2 W current_state [1:0] $end
$var reg 1 X dispReady $end
$var reg 4 Y myChar0 [3:0] $end
$var reg 4 Z myChar1 [3:0] $end
$var reg 4 [ myChar2 [3:0] $end
$var reg 4 \ myChar3 [3:0] $end
$var reg 2 ] next_state [1:0] $end
$var reg 1 ^ set $end
$var reg 1 _ setReady $end
$upscope $end
$scope module Ut $end
$var wire 8 ` Tx_Data [7:0] $end
$var wire 1 a Tx_EN $end
$var wire 1 b Tx_WR $end
$var wire 1 c Tx_sample_ENABLE $end
$var wire 3 d baud_select [2:0] $end
$var wire 1 K clk $end
$var wire 1 e reset $end
$var reg 1 f TxD $end
$var reg 1 g Tx_BUSY $end
$var reg 1 h current_state $end
$var reg 1 i next_state $end
$var reg 1 j parity_bit $end
$var reg 4 k tx_counter [3:0] $end
$scope module baud_controller_tx_instance $end
$var wire 3 l baud_select [2:0] $end
$var wire 1 K clk $end
$var wire 1 e reset $end
$var reg 16 m baudCounter [15:0] $end
$var reg 16 n divisor [15:0] $end
$var reg 1 o sample_ENABLE $end
$upscope $end
$upscope $end
$scope module Ur $end
$var wire 1 - RxD $end
$var wire 1 p Rx_EN $end
$var wire 1 q Rx_sample_ENABLE $end
$var wire 3 r baud_select [2:0] $end
$var wire 1 K clk $end
$var wire 1 e reset $end
$var reg 8 s Rx_DATA [7:0] $end
$var reg 1 t Rx_FERROR $end
$var reg 1 u Rx_PERROR $end
$var reg 8 v Rx_POS_DATA [7:0] $end
$var reg 1 w Rx_VALID $end
$var reg 4 x Rx_counter [3:0] $end
$var reg 1 y Rx_parity_bit $end
$var reg 1 z Tx_parity_bit $end
$var reg 1 { current_state $end
$var reg 1 | next_state $end
$var reg 1 } state $end
$scope module baud_controller_rx_instance $end
$var wire 3 ~ baud_select [2:0] $end
$var wire 1 K clk $end
$var wire 1 e reset $end
$var reg 16 !" baudCounter [15:0] $end
$var reg 16 "" divisor [15:0] $end
$var reg 1 #" sample_ENABLE $end
$upscope $end
$upscope $end
$upscope $end
$enddefinitions $end
#0
$dumpvars
0#"
b11011 ""
b1 !"
b111 ~
0}
1|
1{
0z
0y
b0 x
0w
bx v
0u
0t
b0 s
b111 r
0q
1p
0o
b11011 n
b1 m
b111 l
b0 k
0j
1i
0h
0g
1f
0e
b111 d
0c
1b
1a
b10100001 `
0_
0^
b1 ]
bx \
bx [
bx Z
bx Y
0X
b1 W
0V
0U
b0 T
b100 S
b0 R
b1111 Q
b100 P
1O
1N
1M
1L
1K
bx J
bx I
bx H
bx G
bx F
bx E
bx D
bx C
bx B
bx A
bx @
bx ?
b100 >
0=
b1010000110010100 <
1;
b111 :
19
18
b10100001 7
16
05
b0 4
bx 3
bx 2
bx 1
bx 0
0/
0.
1-
0,
0+
0*
b0 )
bx (
bx '
bx &
bx %
1$
1#
1"
1!
$end
#5
09
0b
#10
0;
0K
#20
b10 !"
b10 m
1;
1K
#30
0;
0K
#40
b11 m
b11 !"
1;
1K
#50
0;
0K
#60
b100 !"
b100 m
1;
1K
#70
0;
0K
#80
b101 m
b101 !"
1;
1K
#90
0;
0K
#100
b110 !"
b110 m
1;
1K
#110
0;
0K
#120
b111 m
b111 !"
1;
1K
#130
0;
0K
#140
b1000 !"
b1000 m
1;
1K
#150
0;
0K
#160
b1001 m
b1001 !"
1;
1K
#170
0;
0K
#180
b1010 !"
b1010 m
1;
1K
#190
0;
0K
#200
b1011 m
b1011 !"
1;
1K
#210
0;
0K
#220
b1100 !"
b1100 m
1;
1K
#230
0;
0K
#240
b1101 m
b1101 !"
1;
1K
#250
0;
0K
#260
b1110 !"
b1110 m
1;
1K
#270
0;
0K
#280
b1111 m
b1111 !"
1;
1K
#290
0;
0K
#300
b10000 !"
b10000 m
1;
1K
#310
0;
0K
#320
b10001 m
b10001 !"
1;
1K
#330
0;
0K
#340
b10010 !"
b10010 m
1;
1K
#350
0;
0K
#360
b10011 m
b10011 !"
1;
1K
#370
0;
0K
#380
b10100 !"
b10100 m
1;
1K
#390
0;
0K
#400
b10101 m
b10101 !"
1;
1K
#410
0;
0K
#420
b10110 !"
b10110 m
1;
1K
#430
0;
0K
#440
b10111 m
b10111 !"
1;
1K
#450
0;
0K
#460
b11000 !"
b11000 m
1;
1K
#470
0;
0K
#480
b11001 m
b11001 !"
1;
1K
#490
0;
0K
#500
b11010 !"
b11010 m
1;
1K
#510
0;
0K
#520
b1 k
0f
0-
1g
1.
1h
1o
1c
b0 m
1#"
1q
b0 !"
1;
1K
#530
0;
0K
#540
b1 !"
b1 m
1;
1K
#550
0;
0K
#560
b10 m
b10 !"
1;
1K
#570
0;
0K
#580
b11 !"
b11 m
1;
1K
#590
0;
0K
#600
b100 m
b100 !"
1;
1K
#610
0;
0K
#620
b101 !"
b101 m
1;
1K
#630
0;
0K
#640
b110 m
b110 !"
1;
1K
#650
0;
0K
#660
b111 !"
b111 m
1;
1K
#670
0;
0K
#680
b1000 m
b1000 !"
1;
1K
#690
0;
0K
#700
b1001 !"
b1001 m
1;
1K
#710
0;
0K
#720
b1010 m
b1010 !"
1;
1K
#730
0;
0K
#740
b1011 !"
b1011 m
1;
1K
#750
0;
0K
#760
b1100 m
b1100 !"
1;
1K
#770
0;
0K
#780
b1101 !"
b1101 m
1;
1K
#790
0;
0K
#800
b1110 m
b1110 !"
1;
1K
#810
0;
0K
#820
b1111 !"
b1111 m
1;
1K
#830
0;
0K
#840
b10000 m
b10000 !"
1;
1K
#850
0;
0K
#860
b10001 !"
b10001 m
1;
1K
#870
0;
0K
#880
b10010 m
b10010 !"
1;
1K
#890
0;
0K
#900
b10011 !"
b10011 m
1;
1K
#910
0;
0K
#920
b10100 m
b10100 !"
1;
1K
#930
0;
0K
#940
b10101 !"
b10101 m
1;
1K
#950
0;
0K
#960
b10110 m
b10110 !"
1;
1K
#970
0;
0K
#980
b10111 !"
b10111 m
1;
1K
#990
0;
0K
#1000
b11000 m
b11000 !"
1;
1K
#1010
0;
0K
#1020
b11001 !"
b11001 m
1;
1K
#1030
0;
0K
#1040
b11010 m
b11010 !"
1;
1K
#1050
0;
0K
#1060
b1 x
1}
0#"
0q
b0 !"
0o
0c
b0 m
1;
1K
#1070
0;
0K
#1080
b1 m
b1 !"
1;
1K
#1090
0;
0K
#1100
b10 !"
b10 m
1;
1K
#1110
0;
0K
#1120
b11 m
b11 !"
1;
1K
#1130
0;
0K
#1140
b100 !"
b100 m
1;
1K
#1150
0;
0K
#1160
b101 m
b101 !"
1;
1K
#1170
0;
0K
#1180
b110 !"
b110 m
1;
1K
#1190
0;
0K
#1200
b111 m
b111 !"
1;
1K
#1210
0;
0K
#1220
b1000 !"
b1000 m
1;
1K
#1230
0;
0K
#1240
b1001 m
b1001 !"
1;
1K
#1250
0;
0K
#1260
b1010 !"
b1010 m
1;
1K
#1270
0;
0K
#1280
b1011 m
b1011 !"
1;
1K
#1290
0;
0K
#1300
b1100 !"
b1100 m
1;
1K
#1310
0;
0K
#1320
b1101 m
b1101 !"
1;
1K
#1330
0;
0K
#1340
b1110 !"
b1110 m
1;
1K
#1350
0;
0K
#1360
b1111 m
b1111 !"
1;
1K
#1370
0;
0K
#1380
b10000 !"
b10000 m
1;
1K
#1390
0;
0K
#1400
b10001 m
b10001 !"
1;
1K
#1410
0;
0K
#1420
b10010 !"
b10010 m
1;
1K
#1430
0;
0K
#1440
b10011 m
b10011 !"
1;
1K
#1450
0;
0K
#1460
b10100 !"
b10100 m
1;
1K
#1470
0;
0K
#1480
b10101 m
b10101 !"
1;
1K
#1490
0;
0K
#1500
b10110 !"
b10110 m
1;
1K
#1510
0;
0K
#1520
b10111 m
b10111 !"
1;
1K
#1530
0;
0K
#1540
b11000 !"
b11000 m
1;
1K
#1550
0;
0K
#1560
b11001 m
b11001 !"
1;
1K
#1570
0;
0K
#1580
b11010 !"
b11010 m
1;
1K
#1590
0;
0K
#1600
b10 k
1j
1f
1-
1o
1c
b0 m
1#"
1q
b0 !"
1;
1K
#1610
0;
0K
#1620
b1 !"
b1 m
1;
1K
#1630
0;
0K
#1640
b10 m
b10 !"
1;
1K
#1650
0;
0K
#1660
b11 !"
b11 m
1;
1K
#1670
0;
0K
#1680
b100 m
b100 !"
1;
1K
#1690
0;
0K
#1700
b101 !"
b101 m
1;
1K
#1710
0;
0K
#1720
b110 m
b110 !"
1;
1K
#1730
0;
0K
#1740
b111 !"
b111 m
1;
1K
#1750
0;
0K
#1760
b1000 m
b1000 !"
1;
1K
#1770
0;
0K
#1780
b1001 !"
b1001 m
1;
1K
#1790
0;
0K
#1800
b1010 m
b1010 !"
1;
1K
#1810
0;
0K
#1820
b1011 !"
b1011 m
1;
1K
#1830
0;
0K
#1840
b1100 m
b1100 !"
1;
1K
#1850
0;
0K
#1860
b1101 !"
b1101 m
1;
1K
#1870
0;
0K
#1880
b1110 m
b1110 !"
1;
1K
#1890
0;
0K
#1900
b1111 !"
b1111 m
1;
1K
#1910
0;
0K
#1920
b10000 m
b10000 !"
1;
1K
#1930
0;
0K
#1940
b10001 !"
b10001 m
1;
1K
#1950
0;
0K
#1960
b10010 m
b10010 !"
1;
1K
#1970
0;
0K
#1980
b10011 !"
b10011 m
1;
1K
#1990
0;
0K
#2000
b10100 m
b10100 !"
1;
1K
#2010
0;
0K
#2020
b10101 !"
b10101 m
1;
1K
#2030
0;
0K
#2040
b10110 m
b10110 !"
1;
1K
#2050
0;
0K
#2060
b10111 !"
b10111 m
1;
1K
#2070
0;
0K
#2080
b11000 m
b11000 !"
1;
1K
#2090
0;
0K
#2100
b11001 !"
b11001 m
1;
1K
#2110
0;
0K
#2120
b11010 m
b11010 !"
1;
1K
#2130
0;
0K
#2140
1y
b10 x
bx1 v
0#"
0q
b0 !"
0o
0c
b0 m
1;
1K
#2150
0;
0K
#2160
b1 m
b1 !"
1;
1K
#2170
0;
0K
#2180
b10 !"
b10 m
1;
1K
#2190
0;
0K
#2200
b11 m
b11 !"
1;
1K
#2210
0;
0K
#2220
b100 !"
b100 m
1;
1K
#2230
0;
0K
#2240
b101 m
b101 !"
1;
1K
#2250
0;
0K
#2260
b110 !"
b110 m
1;
1K
#2270
0;
0K
#2280
b111 m
b111 !"
1;
1K
#2290
0;
0K
#2300
b1000 !"
b1000 m
1;
1K
#2310
0;
0K
#2320
b1001 m
b1001 !"
1;
1K
#2330
0;
0K
#2340
b1010 !"
b1010 m
1;
1K
#2350
0;
0K
#2360
b1011 m
b1011 !"
1;
1K
#2370
0;
0K
#2380
b1100 !"
b1100 m
1;
1K
#2390
0;
0K
#2400
b1101 m
b1101 !"
1;
1K
#2410
0;
0K
#2420
b1110 !"
b1110 m
1;
1K
#2430
0;
0K
#2440
b1111 m
b1111 !"
1;
1K
#2450
0;
0K
#2460
b10000 !"
b10000 m
1;
1K
#2470
0;
0K
#2480
b10001 m
b10001 !"
1;
1K
#2490
0;
0K
#2500
b10010 !"
b10010 m
1;
1K
#2510
0;
0K
#2520
b10011 m
b10011 !"
1;
1K
#2530
0;
0K
#2540
b10100 !"
b10100 m
1;
1K
#2550
0;
0K
#2560
b10101 m
b10101 !"
1;
1K
#2570
0;
0K
#2580
b10110 !"
b10110 m
1;
1K
#2590
0;
0K
#2600
b10111 m
b10111 !"
1;
1K
#2610
0;
0K
#2620
b11000 !"
b11000 m
1;
1K
#2630
0;
0K
#2640
b11001 m
b11001 !"
1;
1K
#2650
0;
0K
#2660
b11010 !"
b11010 m
1;
1K
#2670
0;
0K
#2680
b11 k
0f
0-
1o
1c
b0 m
1#"
1q
b0 !"
1;
1K
#2690
0;
0K
#2700
b1 !"
b1 m
1;
1K
#2710
0;
0K
#2720
b10 m
b10 !"
1;
1K
#2730
0;
0K
#2740
b11 !"
b11 m
1;
1K
#2750
0;
0K
#2760
b100 m
b100 !"
1;
1K
#2770
0;
0K
#2780
b101 !"
b101 m
1;
1K
#2790
0;
0K
#2800
b110 m
b110 !"
1;
1K
#2810
0;
0K
#2820
b111 !"
b111 m
1;
1K
#2830
0;
0K
#2840
b1000 m
b1000 !"
1;
1K
#2850
0;
0K
#2860
b1001 !"
b1001 m
1;
1K
#2870
0;
0K
#2880
b1010 m
b1010 !"
1;
1K
#2890
0;
0K
#2900
b1011 !"
b1011 m
1;
1K
#2910
0;
0K
#2920
b1100 m
b1100 !"
1;
1K
#2930
0;
0K
#2940
b1101 !"
b1101 m
1;
1K
#2950
0;
0K
#2960
b1110 m
b1110 !"
1;
1K
#2970
0;
0K
#2980
b1111 !"
b1111 m
1;
1K
#2990
0;
0K
#3000
b10000 m
b10000 !"
1;
1K
#3010
0;
0K
#3020
b10001 !"
b10001 m
1;
1K
#3030
0;
0K
#3040
b10010 m
b10010 !"
1;
1K
#3050
0;
0K
#3060
b10011 !"
b10011 m
1;
1K
#3070
0;
0K
#3080
b10100 m
b10100 !"
1;
1K
#3090
0;
0K
#3100
b10101 !"
b10101 m
1;
1K
#3110
0;
0K
#3120
b10110 m
b10110 !"
1;
1K
#3130
0;
0K
#3140
b10111 !"
b10111 m
1;
1K
#3150
0;
0K
#3160
b11000 m
b11000 !"
1;
1K
#3170
0;
0K
#3180
b11001 !"
b11001 m
1;
1K
#3190
0;
0K
#3200
b11010 m
b11010 !"
1;
1K
#3210
0;
0K
#3220
b11 x
bx01 v
0#"
0q
b0 !"
0o
0c
b0 m
1;
1K
#3230
0;
0K
#3240
b1 m
b1 !"
1;
1K
#3250
0;
0K
#3260
b10 !"
b10 m
1;
1K
#3270
0;
0K
#3280
b11 m
b11 !"
1;
1K
#3290
0;
0K
#3300
b100 !"
b100 m
1;
1K
#3310
0;
0K
#3320
b101 m
b101 !"
1;
1K
#3330
0;
0K
#3340
b110 !"
b110 m
1;
1K
#3350
0;
0K
#3360
b111 m
b111 !"
1;
1K
#3370
0;
0K
#3380
b1000 !"
b1000 m
1;
1K
#3390
0;
0K
#3400
b1001 m
b1001 !"
1;
1K
#3410
0;
0K
#3420
b1010 !"
b1010 m
1;
1K
#3430
0;
0K
#3440
b1011 m
b1011 !"
1;
1K
#3450
0;
0K
#3460
b1100 !"
b1100 m
1;
1K
#3470
0;
0K
#3480
b1101 m
b1101 !"
1;
1K
